rinoh_typeface_dejavusans/AUTHORS
rinoh_typeface_dejavusans/BUGS
rinoh_typeface_dejavusans/DejaVuSans-Bold.ttf
rinoh_typeface_dejavusans/DejaVuSans-BoldOblique.ttf
rinoh_typeface_dejavusans/DejaVuSans-ExtraLight.ttf
rinoh_typeface_dejavusans/DejaVuSans-Oblique.ttf
rinoh_typeface_dejavusans/DejaVuSans.ttf
rinoh_typeface_dejavusans/DejaVuSansCondensed-Bold.ttf
rinoh_typeface_dejavusans/DejaVuSansCondensed-BoldOblique.ttf
rinoh_typeface_dejavusans/DejaVuSansCondensed-Oblique.ttf
rinoh_typeface_dejavusans/DejaVuSansCondensed.ttf
rinoh_typeface_dejavusans/LICENSE
rinoh_typeface_dejavusans/NEWS
rinoh_typeface_dejavusans/README.md
rinoh_typeface_dejavusans/__init__.py
rinoh_typeface_dejavusans/langcover.txt
rinoh_typeface_dejavusans/status.txt
rinoh_typeface_dejavusans/unicover.txt
rinoh_typeface_dejavusans-0.1.0.dist-info/METADATA
rinoh_typeface_dejavusans-0.1.0.dist-info/WHEEL
rinoh_typeface_dejavusans-0.1.0.dist-info/entry_points.txt
rinoh_typeface_dejavusans-0.1.0.dist-info/top_level.txt
rinoh_typeface_dejavusans-0.1.0.dist-info/RECORD
